Metadata-Version: 2.1
Name: vaultify
Version: 0.0.1
Summary: Python's secret keeper for your Passwords. (Your python password manager)
Home-page: https://github.com/ArthurKakande/vaultify
Author: Arthur Kakande
Author-email: kaksarthur@gmail.com
License: MIT license
Keywords: vaultify
Classifier: Intended Audience :: Developers
Classifier: License :: OSI Approved :: MIT License
Classifier: Natural Language :: English
Classifier: Programming Language :: Python :: 3
Classifier: Programming Language :: Python :: 3.8
Classifier: Programming Language :: Python :: 3.9
Classifier: Programming Language :: Python :: 3.10
Classifier: Programming Language :: Python :: 3.11
Requires-Python: >=3.8
License-File: LICENSE
